pytest_resilient_circuits/LICENSE
pytest_resilient_circuits/__init__.py
pytest_resilient_circuits/circuits_fixtures.py
pytest_resilient_circuits/misc.py
pytest_resilient_circuits/mocks.py
pytest_resilient_circuits/plugin.py
pytest_resilient_circuits/resilient_circuits_fixtures.py
pytest_resilient_circuits/data/200_JSON_GET__actions.json
pytest_resilient_circuits/data/200_JSON_GET__attachments.json
pytest_resilient_circuits/data/200_JSON_GET__connectors.json
pytest_resilient_circuits/data/200_JSON_GET__const.json
pytest_resilient_circuits/data/200_JSON_GET__functions.json
pytest_resilient_circuits/data/200_JSON_GET__incidents_2314.json
pytest_resilient_circuits/data/200_JSON_GET__layouts.json
pytest_resilient_circuits/data/200_JSON_GET__message_destinations.json
pytest_resilient_circuits/data/200_JSON_GET__task.json
pytest_resilient_circuits/data/200_JSON_GET__types.json
pytest_resilient_circuits/data/200_JSON_GET__types_artifact.json
pytest_resilient_circuits/data/200_JSON_GET__types_function_fields.json
pytest_resilient_circuits/data/200_JSON_GET__types_incident.json
pytest_resilient_circuits/data/200_JSON_GET__types_incident_fields.json
pytest_resilient_circuits/data/200_JSON_GET__wiki100.json
pytest_resilient_circuits/data/200_JSON_GET__wiki3.json
pytest_resilient_circuits/data/200_JSON_GET__wikis.json
pytest_resilient_circuits/data/200_JSON_POST__attachment.json
pytest_resilient_circuits/data/200_JSON_POST__table_data.json
pytest_resilient_circuits/data/200_JSON_PUT__layouts.json
pytest_resilient_circuits/shared_mock_data/__init__.py
pytest_resilient_circuits/shared_mock_data/mock_constants.py
pytest_resilient_circuits-51.0.7.2.16540.dist-info/METADATA
pytest_resilient_circuits-51.0.7.2.16540.dist-info/WHEEL
pytest_resilient_circuits-51.0.7.2.16540.dist-info/entry_points.txt
pytest_resilient_circuits-51.0.7.2.16540.dist-info/top_level.txt
pytest_resilient_circuits-51.0.7.2.16540.dist-info/RECORD
