Metadata-Version: 2.4
Name: pytest_resilient_circuits
Version: 51.0.7.2.16540
Summary: Resilient Circuits fixtures for PyTest
Home-page: https://github.com/ibmresilient/resilient-python-api/tree/main/resilient-resilient-circuits
Author: IBM SOAR
License: MIT
Project-URL: Documentation, https://ibm.biz/soar-docs
Project-URL: API Docs, https://ibm.biz/soar-python-docs
Project-URL: IBM Community, https://ibm.biz/soarcommunity
Keywords: ibm,soar,pytest,resilient,resilient-circuits,circuits
Classifier: Programming Language :: Python :: 3.9
Classifier: Programming Language :: Python :: 3.11
Classifier: Programming Language :: Python :: 3.12
Requires-Python: >=3.9
Requires-Dist: resilient-circuits>=51.0.2.1
Requires-Dist: requests-mock~=1.12
Requires-Dist: ConfigParser~=5.2
Requires-Dist: pytest~=7.0
